odoo8_addon_project_stage_closed-8.0.1.0.0.99.dev13-py2.7-nspkg.pth
odoo8_addon_project_stage_closed-8.0.1.0.0.99.dev13.dist-info/DESCRIPTION.rst
odoo8_addon_project_stage_closed-8.0.1.0.0.99.dev13.dist-info/METADATA
odoo8_addon_project_stage_closed-8.0.1.0.0.99.dev13.dist-info/RECORD
odoo8_addon_project_stage_closed-8.0.1.0.0.99.dev13.dist-info/WHEEL
odoo8_addon_project_stage_closed-8.0.1.0.0.99.dev13.dist-info/metadata.json
odoo8_addon_project_stage_closed-8.0.1.0.0.99.dev13.dist-info/namespace_packages.txt
odoo8_addon_project_stage_closed-8.0.1.0.0.99.dev13.dist-info/top_level.txt
odoo_addons/project_stage_closed/README.rst
odoo_addons/project_stage_closed/__init__.py
odoo_addons/project_stage_closed/__openerp__.py
odoo_addons/project_stage_closed/i18n/de.po
odoo_addons/project_stage_closed/i18n/es.po
odoo_addons/project_stage_closed/i18n/fi.po
odoo_addons/project_stage_closed/i18n/fr.po
odoo_addons/project_stage_closed/i18n/nb.po
odoo_addons/project_stage_closed/i18n/project_stage_closed.pot
odoo_addons/project_stage_closed/i18n/pt.po
odoo_addons/project_stage_closed/i18n/pt_BR.po
odoo_addons/project_stage_closed/i18n/pt_PT.po
odoo_addons/project_stage_closed/i18n/sl.po
odoo_addons/project_stage_closed/i18n/sv.po
odoo_addons/project_stage_closed/models/__init__.py
odoo_addons/project_stage_closed/models/task_stage.py
odoo_addons/project_stage_closed/static/description/icon.png
odoo_addons/project_stage_closed/views/task_stage.xml
